neonmob/__init__.py
neonmob-0.0.0.dev0.dist-info/DESCRIPTION.rst
neonmob-0.0.0.dev0.dist-info/METADATA
neonmob-0.0.0.dev0.dist-info/RECORD
neonmob-0.0.0.dev0.dist-info/WHEEL
neonmob-0.0.0.dev0.dist-info/metadata.json
neonmob-0.0.0.dev0.dist-info/top_level.txt
