Metadata-Version: 2.0
Name: neonmob
Version: 0.0.0.dev0
Summary: An API client library for NeonMob.com
Home-page: https://github.com/sgerrand/neonmob.py
Author: Sasha Gerrand
Author-email: pypi-neonmob@sgerrand.com
License: MIT
Keywords: neonmob http api httpclients web
Platform: UNKNOWN
Classifier: Development Status :: 3 - Alpha
Classifier: Intended Audience :: Developers
Classifier: License :: OSI Approved :: MIT License
Classifier: Operating System :: OS Independent
Classifier: Programming Language :: Python
Classifier: Programming Language :: Python :: 2
Classifier: Programming Language :: Python :: 3
Classifier: Topic :: Software Development :: Libraries :: Python Modules
Classifier: Topic :: Software Development :: Testing
Classifier: Topic :: Utilities
Provides-Extra: dev
Requires-Dist: check-manifest; extra == 'dev'
Provides-Extra: test
Requires-Dist: coverage; extra == 'test'
